{
    "greetings": [
        {
            "words": ["龍", "馬", "精", "神"],
            "meaning": "龍馬精神",
            "wrong_words": ["福", "天", "地", "人", "山", "水", "雲", "風"]
        },
        {
            "words": ["恭", "喜", "發", "財"],
            "meaning": "恭喜發財",
            "wrong_words": ["福", "樂", "安", "康", "富", "貴", "榮", "華"]
        },
        {
            "words": ["萬", "事", "如", "意"],
            "meaning": "萬事如意",
            "wrong_words": ["福", "祿", "壽", "德", "善", "美", "樂", "安"]
        },
        {
            "words": ["年", "年", "有", "餘"],
            "meaning": "年年有餘",
            "wrong_words": ["福", "祿", "壽", "喜", "樂", "安", "康", "泰"]
        },
        {
            "words": ["大", "吉", "大", "利"],
            "meaning": "大吉大利",
            "wrong_words": ["福", "祿", "壽", "喜", "樂", "安", "康", "泰"]
        },
        {
            "words": ["福", "祿", "壽", "喜"],
            "meaning": "福祿壽喜",
            "wrong_words": ["德", "善", "美", "樂", "安", "康", "泰", "富"]
        },
        {
            "words": ["步", "步", "高", "升"],
            "meaning": "步步高升",
            "wrong_words": ["福", "祿", "壽", "喜", "德", "善", "美", "樂"]
        },
        {
            "words": ["吉", "祥", "如", "意"],
            "meaning": "吉祥如意",
            "wrong_words": ["福", "樂", "安", "康", "泰", "富", "貴", "榮"]
        },
        {
            "words": ["心", "想", "事", "成"],
            "meaning": "心想事成",
            "wrong_words": ["福", "祿", "壽", "喜", "樂", "安", "康", "泰"]
        },
        {
            "words": ["開", "心", "快", "樂"],
            "meaning": "開心快樂",
            "wrong_words": ["福", "祿", "壽", "吉", "祥", "安", "康", "富"]
        },
        {
            "words": ["金", "銀", "滿", "屋"],
            "meaning": "金銀滿屋",
            "wrong_words": ["福", "祿", "壽", "喜", "樂", "安", "康", "泰"]
        },
        {
            "words": ["生", "意", "興", "隆"],
            "meaning": "生意興隆",
            "wrong_words": ["福", "祿", "壽", "吉", "喜", "安", "康", "富"]
        },
        {
            "words": ["財", "源", "廣", "進"],
            "meaning": "財源廣進",
            "wrong_words": ["福", "祿", "壽", "喜", "樂", "安", "康", "泰"]
        },
        {
            "words": ["平", "安", "快", "樂"],
            "meaning": "平安快樂",
            "wrong_words": ["福", "祿", "壽", "吉", "喜", "安", "康", "富"]
        },
        {
            "words": ["春", "風", "得", "意"],
            "meaning": "春風得意",
            "wrong_words": ["福", "祿", "壽", "喜", "樂", "安", "康", "泰"]
        },
        {
            "words": ["一", "帆", "風", "順"],
            "meaning": "一帆風順",
            "wrong_words": ["福", "祿", "壽", "喜", "樂", "安", "康", "富"]
        },
        {
            "words": ["蒸", "蒸", "日", "上"],
            "meaning": "蒸蒸日上",
            "wrong_words": ["福", "祿", "壽", "喜", "樂", "安", "康", "泰"]
        },
        {
            "words": ["鴻", "運", "當", "前"],
            "meaning": "鴻運當前",
            "wrong_words": ["福", "祿", "壽", "喜", "樂", "安", "康", "富"]
        },
        {
            "words": ["吉", "星", "高", "照"],
            "meaning": "吉星高照",
            "wrong_words": ["福", "祿", "壽", "喜", "樂", "安", "康", "泰"]
        }
    ],
    "currentVersion": "2025"
}